openget/__init__.py
openget/__main__.py
openget/env.py
openget/setting.py
openget/util.py
openget/db/__init__.py
openget/db/db.py
openget/db/db_mysql.py
openget/db/db_oracle.py
openget/db/db_oss.py
openget/db/db_postgresql.py
openget/db/db_redis.py
openget/db/db_sqlite.py
openget/db/util.py
openget/network/__init__.py
openget/network/downloader.py
openget/network/proxy.py
openget/network/request.py
openget/network/response.py
openget/spiders/__init__.py
openget/spiders/base.py
openget/spiders/batch_spider.py
openget/utils/__init__.py
openget/utils/log.py
openget/utils/s3.py
openget/utils/message/__init__.py
openget/utils/message/dingtalk.py
openget-0.3.7.dist-info/LICENSE
openget-0.3.7.dist-info/METADATA
openget-0.3.7.dist-info/WHEEL
openget-0.3.7.dist-info/top_level.txt
openget-0.3.7.dist-info/RECORD
