Metadata-Version: 2.1
Name: openget
Version: 0.3.7
Summary: A Spider FrameWork
Home-page: https://github.com/dytttf/openget
Author: Dytttf
Author-email: dytttf@foxmail.com
License: BSD
Keywords: openget,spider,batch-spider
Classifier: Development Status :: 3 - Alpha
Classifier: Framework :: Scrapy
Classifier: Operating System :: POSIX
Classifier: Programming Language :: Python :: 3 :: Only
Classifier: License :: OSI Approved :: BSD License
License-File: LICENSE
Requires-Dist: gevent
Requires-Dist: pymysql
Requires-Dist: redis (>=3.0.0)
Requires-Dist: better-exceptions
Requires-Dist: tqdm
Requires-Dist: httpx[http2]
Requires-Dist: user-agent2
Requires-Dist: urllib3
Requires-Dist: python-dotenv
